monday/__init__.py
monday/__version__.py
monday/client.py
monday/exceptions.py
monday/query_joins.py
monday/utils.py
monday/graphqlclient/client.py
monday/resources/__init__.py
monday/resources/account.py
monday/resources/base.py
monday/resources/boards.py
monday/resources/complexity.py
monday/resources/groups.py
monday/resources/items.py
monday/resources/notification.py
monday/resources/tags.py
monday/resources/updates.py
monday/resources/users.py
monday/resources/webhooks.py
monday/resources/workspaces.py
express_integrations_monday-1.0.19.dist-info/LICENSE
express_integrations_monday-1.0.19.dist-info/METADATA
express_integrations_monday-1.0.19.dist-info/WHEEL
express_integrations_monday-1.0.19.dist-info/top_level.txt
express_integrations_monday-1.0.19.dist-info/RECORD
