Metadata-Version: 2.1
Name: express-integrations-monday
Version: 1.0.19
Summary: A Python client library for Monday.com
Home-page: https://github.com/expressintegrations/monday
Author: Express Integrations
Author-email: jasper@expressintegrations.com
License: BSD
Classifier: Programming Language :: Python :: 3
Classifier: Programming Language :: Python :: 3.6
Classifier: Programming Language :: Python :: 3.7
Classifier: Programming Language :: Python :: 3.8
Classifier: Operating System :: OS Independent
Requires-Python: >=3.6
License-File: LICENSE
Requires-Dist: requests (==2.26.0)
Requires-Dist: backoff (==2.1.2)
